[
       {
              "name": "Charles d'Espeville",
              "desc": "",
              "url": "",
              "img": ""
       },
       {
              "name": "Consistoire de Neuchâtel",
              "desc": "Conseil ecclésiastique du canton de Neuchâtel du XVIe au XVIIIe siècle",
              "url": "http://www.wikidata.org/entity/Q131694038",
              "img": ""
       },
       {
              "name": "Martin Bucer (1491 - 1551)",
              "desc": "réformateur protestant alsacien",
              "url": "http://www.wikidata.org/entity/Q318622",
              "img": "http://commons.wikimedia.org/wiki/Special:FilePath/Martin%20Buzer%20%28Bucer%29.jpg"
       },
       {
              "name": "Yolande de Brederode",
              "desc": "Aristocrate de la maison des comtes de Hollande et épouse de Jacques de Bourgogne",
              "url": "http://www.wikidata.org/entity/Q56000839",
              "img": ""
       },
       {
              "name": "Louis du Tillet",
              "desc": "prêtre catholique français",
              "url": "http://www.wikidata.org/entity/Q3263586",
              "img": ""
       },
       {
              "name": "Wolfgang Fabricius Köpfel Capiton (1478 - 1541)",
              "desc": "réformateur et théologien alsacien (1478-1541)",
              "url": "http://www.wikidata.org/entity/Q1368362",
              "img": "http://commons.wikimedia.org/wiki/Special:FilePath/WolfgangCapito.jpg"
       },
       {
              "name": "François Ier de France (1494 - 1547)",
              "desc": "roi de France de 1515 à 1547",
              "url": "http://www.wikidata.org/entity/Q129857",
              "img": "http://commons.wikimedia.org/wiki/Special:FilePath/Fran%C3%A7ois%20Ier%20Louvre.jpg"
       },
       {
              "name": "Édouard VI d'Angleterre (1537 - 1553)",
              "desc": "roi d'Angleterre de 1547 à 1553",
              "url": "http://www.wikidata.org/entity/Q83229",
              "img": "http://commons.wikimedia.org/wiki/Special:FilePath/Edward%20VI%20of%20England%20c.%201546.jpg"
       },
       {
              "name": "Jean du Tillet",
              "desc": "Évêque de Saint-Brieuc et Meaux",
              "url": "http://www.wikidata.org/entity/Q3175826",
              "img": ""
       },
       {
              "name": "Antoine de Bourbon (1518 - 1562)",
              "desc": "roi consort de Navarre",
              "url": "http://www.wikidata.org/entity/Q310334",
              "img": "http://commons.wikimedia.org/wiki/Special:FilePath/Unknown%20-%20Portrait%20of%20Anthony%20of%20Bourbon%20%281518%E2%80%931562%29%2C%20King%20of%20Navarre%20-%20MNK%20XII-294%20-%20National%20Museum%20Krak%C3%B3w.jpg"
       },
       {
              "name": "Guillaume Farel (1489 - 1565)",
              "desc": "réformateur d'origine dauphinoise en Suisse romande",
              "url": "http://www.wikidata.org/entity/Q435456",
              "img": "http://commons.wikimedia.org/wiki/Special:FilePath/William-Farel.jpg"
       },
       {
              "name": "Renée de France (1510 - 1574)",
              "desc": "aristocrate française",
              "url": "http://www.wikidata.org/entity/Q235841",
              "img": "http://commons.wikimedia.org/wiki/Special:FilePath/Renee%20de%20france.jpg"
       },
       {
              "name": "Consistoire de Genève",
              "desc": "Conseil ecclésiastique suisse du XVIe, XVIIe et XVIIIe siècles",
              "url": "http://www.wikidata.org/entity/Q2994627",
              "img": ""
       },
       {
              "name": "Jacques de Bourgogne",
              "desc": "Seigneur de Fallais et de Bréda en Brabant, noble flamand et correspondant de Calvin qui a initialement soutenu le réformateur",
              "url": "http://www.wikidata.org/entity/Q6120956",
              "img": ""
       },
       {
              "name": "Philippe Mélanchthon (1497 - 1560)",
              "desc": "humaniste, philosophe et réformateur protestant allemand",
              "url": "http://www.wikidata.org/entity/Q76325",
              "img": "http://commons.wikimedia.org/wiki/Special:FilePath/PhilippMelanchthon.jpg"
       },
       {
              "name": "Sébastien Castellion (1515 - 1563)",
              "desc": "humaniste, bibliste et théologien protestant français",
              "url": "http://www.wikidata.org/entity/Q919119",
              "img": "http://commons.wikimedia.org/wiki/Special:FilePath/SebastianCastellio.jpg"
       },
       {
              "name": "Laurent de Normandie (1510 - 1569)",
              "desc": "juriste franco-genevois",
              "url": "http://www.wikidata.org/entity/Q15967055",
              "img": "http://commons.wikimedia.org/wiki/Special:FilePath/Laurent%20de%20Normandie.jpg"
       },
       {
              "name": "Pierre Viret (1511 - 1571)",
              "desc": "Réformateur vaudois",
              "url": "http://www.wikidata.org/entity/Q123337",
              "img": "http://commons.wikimedia.org/wiki/Special:FilePath/PierreViret.jpg"
       },
       {
              "name": "Anne de Parthenay",
              "desc": "Aristocrate française et érudite qui a été associée à Calvin, dame de compagnie de la duchesse d'Este",
              "url": "http://www.wikidata.org/entity/Q99539414",
              "img": ""
       },
       {
              "name": "Roberte Le Lyeur",
              "desc": "épouse de Guillaume Budé",
              "url": "http://www.wikidata.org/entity/Q108743308",
              "img": ""
       },
       {
              "name": "Charles Quint (1500 - 1558)",
              "desc": "monarque et empereur d'origine flamande",
              "url": "http://www.wikidata.org/entity/Q32500",
              "img": "http://commons.wikimedia.org/wiki/Special:FilePath/Portrait%20of%20Charles%20V%2C%20Holy%20Roman%20Emperor%2C%20seated%20%281500%E2%80%931558%29%2C%20formerly%20attributed%20to%20Titian%20%28Alte%20Pinakothek%2C%20Munich%29.jpg"
       }
]